keycloak/__init__.py
keycloak/dataclass.py
keycloak/token.py
keycloak/user.py
keycloak/util.py
keycloak_basic-1.2.1.dist-info/LICENSE
keycloak_basic-1.2.1.dist-info/METADATA
keycloak_basic-1.2.1.dist-info/WHEEL
keycloak_basic-1.2.1.dist-info/top_level.txt
keycloak_basic-1.2.1.dist-info/RECORD
