Metadata-Version: 2.1
Name: keycloak-basic
Version: 1.2.1
Summary: Keycloak Authenticator
Home-page: https://github.com/iTecAI/Keycloak-Basic
Author: Dax Harris
License: MIT
Platform: UNKNOWN
Classifier: License :: OSI Approved :: MIT License
Classifier: Programming Language :: Python :: 3
Classifier: Programming Language :: Python :: 3.7
Classifier: Programming Language :: Python :: 3.10
License-File: LICENSE
Requires-Dist: requests
